[
  {
    "file": "hotel_review1.csv",
    "folder": "C:\\Users\\dso3hc\\Downloads\\Implement\\SemAE\\outputs\\hasos_english_only\\hotel_review1",
    "stats": {
      "input_csv": "C:\\Users\\dso3hc\\Downloads\\Implement\\hotel_review1.csv",
      "detector_rule": "English-like if repaired text has at least 8 alphabetic chars, ASCII-letter ratio >= 0.86, at least 3 normalized tokens, and either 2 common English marker hits, or 1 marker plus 1 hotel-domain hit, or 2 hotel-domain hits with ASCII ratio >= 0.94.",
      "total_rows": 607260,
      "nonempty_reviews": 607260,
      "english_reviews": 270658,
      "english_sentences": 850307,
      "rejected_reviews": 336602,
      "reject_reasons": {
        "low_ascii_letter_ratio": 234758,
        "not_enough_english_markers": 70564,
        "too_few_tokens": 7242,
        "too_few_letters": 9285,
        "no_english_sentences": 14753
      },
      "top_english_hotels": [
        {
          "hotel_id": "booking_02157",
          "english_reviews": 1327
        },
        {
          "hotel_id": "booking_02806",
          "english_reviews": 1091
        },
        {
          "hotel_id": "booking_02757",
          "english_reviews": 985
        },
        {
          "hotel_id": "booking_02798",
          "english_reviews": 942
        },
        {
          "hotel_id": "booking_02840",
          "english_reviews": 933
        },
        {
          "hotel_id": "booking_02787",
          "english_reviews": 906
        },
        {
          "hotel_id": "booking_02813",
          "english_reviews": 884
        },
        {
          "hotel_id": "booking_02886",
          "english_reviews": 821
        },
        {
          "hotel_id": "booking_02810",
          "english_reviews": 815
        },
        {
          "hotel_id": "booking_02897",
          "english_reviews": 812
        },
        {
          "hotel_id": "booking_02748",
          "english_reviews": 808
        },
        {
          "hotel_id": "booking_01182",
          "english_reviews": 757
        },
        {
          "hotel_id": "booking_02802",
          "english_reviews": 701
        },
        {
          "hotel_id": "booking_11979",
          "english_reviews": 698
        },
        {
          "hotel_id": "booking_02859",
          "english_reviews": 674
        },
        {
          "hotel_id": "booking_12019",
          "english_reviews": 660
        },
        {
          "hotel_id": "booking_02817",
          "english_reviews": 641
        },
        {
          "hotel_id": "booking_12020",
          "english_reviews": 621
        },
        {
          "hotel_id": "booking_03039",
          "english_reviews": 575
        },
        {
          "hotel_id": "booking_03208",
          "english_reviews": 569
        }
      ],
      "sample_kept": [
        {
          "ref_id": "booking_04272_2",
          "hotel_id": "booking_04272",
          "reason": "common_english_markers",
          "ascii_letter_ratio": 1.0,
          "marker_hits": 18,
          "hotel_hits": 3,
          "review": "The staff were very kind and helpful. The dog was also a sweetheart. The water pressure in the shower was weak. The bed mat was also hard, so it was hard for me to sleep."
        },
        {
          "ref_id": "booking_04276_11",
          "hotel_id": "booking_04276",
          "reason": "common_english_markers",
          "ascii_letter_ratio": 1.0,
          "marker_hits": 4,
          "hotel_hits": 2,
          "review": "Location is superb, indoor decor with live plants top notch, trained staff, very good cook. Luxurious experience all the way. -"
        },
        {
          "ref_id": "booking_04305_13",
          "hotel_id": "booking_04305",
          "reason": "common_english_markers",
          "ascii_letter_ratio": 1.0,
          "marker_hits": 7,
          "hotel_hits": 1,
          "review": "smelly roomaccess going to the room is a bit hard. especially when its raining helpful staff"
        }
      ],
      "sample_rejected": [
        {
          "ref_id": "booking_04287_0",
          "reason": "low_ascii_letter_ratio",
          "ascii_letter_ratio": 0.717391304347826,
          "marker_hits": 2,
          "hotel_hits": 0,
          "review": "Rất thích đệm và giường tại hhostels vì rất êm và cũng private. Địa điểm gần trung tâm mộc và các điểm checkin đẹp khác ở mộc châu. Nhà hàng thuộc A Pao ngay kế bên, đồ ăn rất ngon"
        },
        {
          "ref_id": "booking_04272_1",
          "reason": "low_ascii_letter_ratio",
          "ascii_letter_ratio": 0.6666666666666666,
          "marker_hits": 0,
          "hotel_hits": 0,
          "review": "Chỗ ở sạch sẽ, ấm cúng. Chị chủ rất nhiệt tình và chu đáo."
        },
        {
          "ref_id": "booking_04325_3",
          "reason": "low_ascii_letter_ratio",
          "ascii_letter_ratio": 0.6578947368421053,
          "marker_hits": 0,
          "hotel_hits": 0,
          "review": "Gọi điện và nhắn tin hỏi nhà nghỉ thái độ rất kém"
        }
      ],
      "english_ratio": 0.4457036524717584
    },
    "overall": {
      "review_count": 270658,
      "sentence_count": 850307,
      "aspect_summary_cover": 0.7337455160783536,
      "macro_cec": 0.5582860587386965,
      "weighted_cec": 0.5624271139242581,
      "matched_aspects": 29,
      "aspect_count": 29,
      "rouge_note": "ROUGE-1/2/L from the SemAE paper requires human gold summaries; this CSV has reviews only, so this trial reports image-formula CEC/ASC instead.",
      "scoring_note": "unique_opinions and cluster_weight are counted on the whole input; summary/CEC/ASC use a capped representative evidence set per aspect.",
      "language_filter": "english",
      "include_vietnamese_aliases": false
    },
    "top_aspects": [
      {
        "aspect": "AM_POOL",
        "group": "AMENITY",
        "measurement_scale": "Pool & Water Facilities",
        "matched_sentences": 116445,
        "unique_opinions": 107100,
        "evidence_used_for_summary": 5000,
        "cluster_weight": 0.038581970180682795,
        "cec": 0.663417501179019,
        "asc_contribution": 0.031181160612953635,
        "summary": [
          "The staff was very nice, the room was super comfortable and clean and the location is beautiful!",
          "The room was very clean and comfortable.",
          "The room was very clean and spacious."
        ]
      },
      {
        "aspect": "EXP_OVERALL",
        "group": "EXPERIENCE",
        "measurement_scale": "Overall Stay Experience",
        "matched_sentences": 101284,
        "unique_opinions": 93538,
        "evidence_used_for_summary": 5000,
        "cluster_weight": 0.03813092764322797,
        "cec": 0.480561913825877,
        "asc_contribution": 0.03004066093823138,
        "summary": [
          "The Home trek from Sapa town to the homestay was the highlight of our stay, and it was an unforgettable experience for our family.",
          "The view from the room was amazing, staff were very helpful, and the food was great.",
          "The room is the best I had in my trip to Vietnam very clean and very big and the bed super comfortable and not expensive at all The offer Dinner and breakfast and it's one of the best I had in Vietnam If you want to have one of the best staying in cao bang come here"
        ]
      },
      {
        "aspect": "FAC_BATH",
        "group": "FACILITY",
        "measurement_scale": "Bathroom & Sanitary Area",
        "matched_sentences": 130365,
        "unique_opinions": 121174,
        "evidence_used_for_summary": 5000,
        "cluster_weight": 0.03899326858441453,
        "cec": 0.6390490502696196,
        "asc_contribution": 0.029697370420632706,
        "summary": [
          "The room was very clean and comfortable.",
          "The staff was very nice, the room was super comfortable and clean and the location is beautiful!",
          "The room was very nice and clean."
        ]
      },
      {
        "aspect": "SER_ATTITUDE",
        "group": "SERVICE",
        "measurement_scale": "Staff Attitude & Hospitality",
        "matched_sentences": 170019,
        "unique_opinions": 151202,
        "evidence_used_for_summary": 5000,
        "cluster_weight": 0.03973078500832228,
        "cec": 0.697359819933331,
        "asc_contribution": 0.029216475788789067,
        "summary": [
          "The staff was very helpful and friendly.",
          "The staff very friendly and helpful.",
          "The staff is very friendly and helpful."
        ]
      },
      {
        "aspect": "FAC_BUILDING",
        "group": "FACILITY",
        "measurement_scale": "Building Infrastructure",
        "matched_sentences": 49712,
        "unique_opinions": 48602,
        "evidence_used_for_summary": 5000,
        "cluster_weight": 0.035949924016609486,
        "cec": 0.5015539742464805,
        "asc_contribution": 0.02917042206230123,
        "summary": [
          "The room was really comfortable with a lovely view of the mountains, and the property was in a nice location in the village.",
          "The view was amazing and the room was very clean and modern.",
          "The property is beautiful and the rooms are clean and comfortable."
        ]
      },
      {
        "aspect": "FAC_INTERIOR",
        "group": "FACILITY",
        "measurement_scale": "Interior Design & Ambience",
        "matched_sentences": 43981,
        "unique_opinions": 42721,
        "evidence_used_for_summary": 5000,
        "cluster_weight": 0.03552027734179142,
        "cec": 0.5991414406485153,
        "asc_contribution": 0.028800198848911263,
        "summary": [
          "The staff was very nice, the room was super comfortable and clean and the location is beautiful!",
          "The breakfast was great with a beautiful view and the rooms are very comfortable and clean.",
          "The room is beautiful and clean, with a nice view."
        ]
      },
      {
        "aspect": "AM_FOOD",
        "group": "AMENITY",
        "measurement_scale": "Food & Beverage",
        "matched_sentences": 141603,
        "unique_opinions": 131420,
        "evidence_used_for_summary": 5000,
        "cluster_weight": 0.039263673629652086,
        "cec": 0.5607532091814887,
        "asc_contribution": 0.028467261565636538,
        "summary": [
          "The view from the room was amazing, staff were very helpful, and the food was great.",
          "The staff was very friendly and helpful and the view is amazing.",
          "The breakfast was amazing."
        ]
      },
      {
        "aspect": "FAC_ROOM",
        "group": "FACILITY",
        "measurement_scale": "Room, Bed & Sleep Quality",
        "matched_sentences": 248301,
        "unique_opinions": 234128,
        "evidence_used_for_summary": 5000,
        "cluster_weight": 0.04118740853705079,
        "cec": 0.6184438578381283,
        "asc_contribution": 0.028228963463796622,
        "summary": [
          "The room was clean and the bed very comfortable.",
          "The room was comfortable and clean.",
          "The room was clean and comfortable."
        ]
      },
      {
        "aspect": "AM_ENT",
        "group": "AMENITY",
        "measurement_scale": "Entertainment & Recreation",
        "matched_sentences": 16111,
        "unique_opinions": 15750,
        "evidence_used_for_summary": 5000,
        "cluster_weight": 0.0321962355584805,
        "cec": 0.4861077590622403,
        "asc_contribution": 0.02759179074711791,
        "summary": [
          "the restaurant itself is also very very basic.- my dad wanted a coffee at 10 PM but there was no coffee available which is just a case of making a pot so it’s just ridiculous - the towels we received had holes in them - there is mold on the roofs in the bathroom - there was construction going on on the first day we were there which was very noisy and went on till 10 PM- the second day there was a school tour with local children who terrorized the area and pool (literally scared guests away from relaxing there) and they did not communicate this visit from them with us- the last day there was some dirt in the pool which they were cleaning but we could not use the pool and again no communication at all while we were literally sitting at the pool- breakfast is okay but very minimal and the same every day Even tough we told almost all of this to the reception employee, there was nothing they did to make our stay better or to change the broken beds or towels etc.",
          "The place is exactly as you see it in pictures and better a really captivating scenery with an outstanding cleaning services our room was very nice especially the view and the size of it and the bathroom The staff were nice enough to store our luggage until check in time Staff at the front desk at the beginning were helpful but in time I saw that they overcharged when requesting taxi for us which happened several times and we had to wait till last day for them to provide electric plug to use our devices and when we asked for laundry to be done they waited till check out time to tell us they forgot to do it We also were surprised by charges of snacks in the room which we thought Complimentaries since there were no menu, tags, or signs of the price Lastly the breakfast buffet is not worth including in the package you get because it is very limited and sometimes not fresh",
          "They have a lovely room, the staff is very friendly, it is very clean, and the food is also very good, the view that you can enjoy from the top is spectacular Taking into account that it is a 5-star hotel, there are some details to improve, no one in the hotel explained to me where everything was located, such as the restaurant, the game room, I discovered it myself, the hotel knew that we were three people and the room did not have things for three people, the game room has devices that do not work, not all the staff speak English, in general I liked it a lot but these details should be improved, thank you"
        ]
      },
      {
        "aspect": "AM_UTILITY",
        "group": "AMENITY",
        "measurement_scale": "Laundry & Utility Services",
        "matched_sentences": 26268,
        "unique_opinions": 25623,
        "evidence_used_for_summary": 5000,
        "cluster_weight": 0.033817349230863575,
        "cec": 0.494977241292958,
        "asc_contribution": 0.02733014429162849,
        "summary": [
          "It was clean in a convenient location and the staff was very friendly.",
          "The bar next to the pool is very convenient, the room is very comfortable, the price was a great value, and the staff are very friendly.",
          "-the location -the place is new so it looks super nice and fancy -they offer you all the services you might need in cat ba such as tours, laundry, taxi, transport to Hanoi, motorbike rental, etc -the room is nice and looked clean -we request to leave the room a little bit after the check out and it was no problem at all -no soap at the bathroom -no one either in the reception or the breakfast spoke a small word of English so you have to use translate for everything -we rent motorcycle and they gave me one with no gasoline at all, we went and charge it, it didn’t work, (took us one hour) next day we change it, no gas again, went to charged it (took us another hour again) -breakfast is one of the worst that I had in hotels in my hole life and in all of Southeast Asia, looks like the place is new and there are a lot of things to improve."
        ]
      }
    ]
  },
  {
    "file": "hotel_review2.csv",
    "folder": "C:\\Users\\dso3hc\\Downloads\\Implement\\SemAE\\outputs\\hasos_english_only\\hotel_review2",
    "stats": {
      "input_csv": "C:\\Users\\dso3hc\\Downloads\\Implement\\hotel_review2.csv",
      "detector_rule": "English-like if repaired text has at least 8 alphabetic chars, ASCII-letter ratio >= 0.86, at least 3 normalized tokens, and either 2 common English marker hits, or 1 marker plus 1 hotel-domain hit, or 2 hotel-domain hits with ASCII ratio >= 0.94.",
      "total_rows": 1150415,
      "nonempty_reviews": 1150384,
      "english_reviews": 602919,
      "english_sentences": 1933276,
      "rejected_reviews": 547465,
      "reject_reasons": {
        "low_ascii_letter_ratio": 288175,
        "not_enough_english_markers": 187102,
        "no_english_sentences": 44587,
        "too_few_tokens": 14237,
        "too_few_letters": 13364
      },
      "top_english_hotels": [
        {
          "hotel_id": "bookingnew_5937937",
          "english_reviews": 3276
        },
        {
          "hotel_id": "bookingnew_367391",
          "english_reviews": 2464
        },
        {
          "hotel_id": "bookingnew_265478",
          "english_reviews": 1785
        },
        {
          "hotel_id": "bookingnew_5433446",
          "english_reviews": 1753
        },
        {
          "hotel_id": "bookingnew_393345",
          "english_reviews": 1646
        },
        {
          "hotel_id": "bookingnew_268022",
          "english_reviews": 1641
        },
        {
          "hotel_id": "bookingnew_4040357",
          "english_reviews": 1636
        },
        {
          "hotel_id": "bookingnew_7384631",
          "english_reviews": 1634
        },
        {
          "hotel_id": "bookingnew_6105345",
          "english_reviews": 1593
        },
        {
          "hotel_id": "bookingnew_9074874",
          "english_reviews": 1582
        },
        {
          "hotel_id": "bookingnew_6930690",
          "english_reviews": 1580
        },
        {
          "hotel_id": "bookingnew_6773578",
          "english_reviews": 1532
        },
        {
          "hotel_id": "bookingnew_351831",
          "english_reviews": 1511
        },
        {
          "hotel_id": "bookingnew_4438946",
          "english_reviews": 1501
        },
        {
          "hotel_id": "bookingnew_9891245",
          "english_reviews": 1494
        },
        {
          "hotel_id": "bookingnew_4857532",
          "english_reviews": 1492
        },
        {
          "hotel_id": "bookingnew_4028344",
          "english_reviews": 1486
        },
        {
          "hotel_id": "bookingnew_2914849",
          "english_reviews": 1341
        },
        {
          "hotel_id": "bookingnew_4464775",
          "english_reviews": 1276
        },
        {
          "hotel_id": "bookingnew_5506520",
          "english_reviews": 1259
        }
      ],
      "sample_kept": [
        {
          "ref_id": "bookingnew_13241654_4",
          "hotel_id": "bookingnew_13241654",
          "reason": "common_english_markers",
          "ascii_letter_ratio": 1.0,
          "marker_hits": 8,
          "hotel_hits": 3,
          "review": "Really nice style, the bed was very comfortable. The staff was extremely kind! We will definitely be back, thank you 🙏🏼"
        },
        {
          "ref_id": "bookingnew_13241654_5",
          "hotel_id": "bookingnew_13241654",
          "reason": "common_english_markers",
          "ascii_letter_ratio": 1.0,
          "marker_hits": 28,
          "hotel_hits": 4,
          "review": "Great location. Walking distance from the center, but quiet, apart from frog singing, which we found funny.\nGood view to the rice paddies especially enjoyable from the hot tube on the balcony. We had to wait cc 20 min for card payment because the receptionist had to go to another place to get it. We were on our way to the airport, do it made us slightly worried."
        },
        {
          "ref_id": "bookingnew_13241654_6",
          "hotel_id": "bookingnew_13241654",
          "reason": "common_english_markers",
          "ascii_letter_ratio": 1.0,
          "marker_hits": 27,
          "hotel_hits": 8,
          "review": "Beautiful hotel with lovely decor. The staff are the most friendly and helpful. Room is beautiful and clean. The bed is super comfy. The shower is one of the best we’ve had at any hotel room. Breakfast is also delicious. It has everything we needed to be comfortable."
        }
      ],
      "sample_rejected": [
        {
          "ref_id": "bookingnew_13241654_0",
          "reason": "low_ascii_letter_ratio",
          "ascii_letter_ratio": 0.7272727272727273,
          "marker_hits": 0,
          "hotel_hits": 0,
          "review": "Khách sạn mới, nhân viên nhiệt tình cực kỳ"
        },
        {
          "ref_id": "bookingnew_13241654_1",
          "reason": "low_ascii_letter_ratio",
          "ascii_letter_ratio": 0.6967741935483871,
          "marker_hits": 3,
          "hotel_hits": 0,
          "review": "Công ty mình nghỉ 2 ngày 1 đêm vào dịp nghỉ tết và có một thời gian rất thoải mái ở đây. Cơ sở hạ tầng rất đẹp, phòng ốc đúng như mô tả và rất sạch sẽ. Vị trí của villa nằm hơi xa so với các khách sạn khác nhưng vẫn gần các địa điểm du lịch Tam Cốc\nVào buổi tối, khuôn viên của villa khá đẹp, bể bơi và đèn được bài trí rất thư giãn và yên tĩnh.\n\nQuản lý và lễ tân có tác phong làm việc ân cần và chu đáo. Hỗ trợ đoàn mình nhận phòng sớm vì đoàn tới sớm hơn giờ check in\n\nThời gian lưu trú ngắn nhưng gia đình tôi rất hài lòng với điều kiện cơ sở vật chất, và cách ứng xử chuyên nghiệp, tận tâm của quản lý villa. Rất recommend mọi người và nếu có dịp trở lại Ninh Bình, đây là một địa điểm tôi vẫn lựa chọn. Villa khi đi đang trong thời gian đầu vận hành nên còn vài thiếu xót nhỏ trong công tác dịch vụ nhưng chấp nhận được."
        },
        {
          "ref_id": "bookingnew_13241654_2",
          "reason": "low_ascii_letter_ratio",
          "ascii_letter_ratio": 0.7857142857142857,
          "marker_hits": 0,
          "hotel_hits": 0,
          "review": "Bữa sáng ngon, nhân viên thân thiện"
        }
      ],
      "english_ratio": 0.5241023866813168
    },
    "overall": {
      "review_count": 602919,
      "sentence_count": 1933276,
      "aspect_summary_cover": 0.7334846561739845,
      "macro_cec": 0.5695109248942614,
      "weighted_cec": 0.5739648842357309,
      "matched_aspects": 29,
      "aspect_count": 29,
      "rouge_note": "ROUGE-1/2/L from the SemAE paper requires human gold summaries; this CSV has reviews only, so this trial reports image-formula CEC/ASC instead.",
      "scoring_note": "unique_opinions and cluster_weight are counted on the whole input; summary/CEC/ASC use a capped representative evidence set per aspect.",
      "language_filter": "english",
      "include_vietnamese_aliases": false
    },
    "top_aspects": [
      {
        "aspect": "FAC_VIEW_LOCATION",
        "group": "FACILITY",
        "measurement_scale": "View, Surroundings & Location",
        "matched_sentences": 356971,
        "unique_opinions": 321132,
        "evidence_used_for_summary": 5000,
        "cluster_weight": 0.03930452195335384,
        "cec": 0.6184727103671651,
        "asc_contribution": 0.03082393358080558,
        "summary": [
          "The bed is comfortable, the room has a good size and was very clean, the staff is super nice and helpful, the breakfast is good and the location is great!",
          "The room was very comfortable, the staff were very friendly and helpful, breakfast was good and the location was great",
          "The location was great and the staff was very friendly."
        ]
      },
      {
        "aspect": "SER_ATTITUDE",
        "group": "SERVICE",
        "measurement_scale": "Staff Attitude & Hospitality",
        "matched_sentences": 381124,
        "unique_opinions": 328886,
        "evidence_used_for_summary": 5000,
        "cluster_weight": 0.03937848014345657,
        "cec": 0.7288913526734343,
        "asc_contribution": 0.030813739296547703,
        "summary": [
          "The staff was very friendly and helpful.",
          "The staff was very helpful and friendly.",
          "The staff were very helpful and friendly."
        ]
      },
      {
        "aspect": "AM_FOOD",
        "group": "AMENITY",
        "measurement_scale": "Food & Beverage",
        "matched_sentences": 322839,
        "unique_opinions": 292661,
        "evidence_used_for_summary": 5000,
        "cluster_weight": 0.0390167438565477,
        "cec": 0.6030244668408926,
        "asc_contribution": 0.03056968270778029,
        "summary": [
          "The room was very comfortable, the staff were very friendly and helpful, breakfast was good and the location was great",
          "The bed is comfortable, the room has a good size and was very clean, the staff is super nice and helpful, the breakfast is good and the location is great!",
          "The location was great and the breakfast was good on the rooftop."
        ]
      },
      {
        "aspect": "FAC_ROOM",
        "group": "FACILITY",
        "measurement_scale": "Room, Bed & Sleep Quality",
        "matched_sentences": 543529,
        "unique_opinions": 503905,
        "evidence_used_for_summary": 5000,
        "cluster_weight": 0.040701097821065596,
        "cec": 0.6137666924722455,
        "asc_contribution": 0.02946847861630715,
        "summary": [
          "The room was clean and nice, very comfortable bed and great location.",
          "The bed was comfortable and the room was clean.",
          "The room was very comfortable, the staff were very friendly and helpful, breakfast was good and the location was great"
        ]
      },
      {
        "aspect": "FAC_BUILDING",
        "group": "FACILITY",
        "measurement_scale": "Building Infrastructure",
        "matched_sentences": 112751,
        "unique_opinions": 109009,
        "evidence_used_for_summary": 5000,
        "cluster_weight": 0.03595542665328182,
        "cec": 0.5488105669596918,
        "asc_contribution": 0.028858246194125463,
        "summary": [
          "The staff are very friendly, the room was great and the location is right in the middle of the old quarter, walking distance to everything.",
          "It was in a great location in the heart of the old quarter!",
          "The hotel is in the perfect location, in the heart of the Old Quarter."
        ]
      },
      {
        "aspect": "AM_POOL",
        "group": "AMENITY",
        "measurement_scale": "Pool & Water Facilities",
        "matched_sentences": 252164,
        "unique_opinions": 226720,
        "evidence_used_for_summary": 5000,
        "cluster_weight": 0.03822536524728491,
        "cec": 0.687716981858676,
        "asc_contribution": 0.027902418850470827,
        "summary": [
          "The room was spacious and very clean.",
          "The room was very spacious and clean.",
          "The room was very clean and spacious."
        ]
      },
      {
        "aspect": "FAC_ENV",
        "group": "FACILITY",
        "measurement_scale": "Noise & Environmental Comfort",
        "matched_sentences": 81000,
        "unique_opinions": 78934,
        "evidence_used_for_summary": 5000,
        "cluster_weight": 0.03495475830711925,
        "cec": 0.522217524395037,
        "asc_contribution": 0.02756036236888979,
        "summary": [
          "A very nice place to stay in a good location in the town, The bed was comfortable and the place was quite quiet.",
          "It is in a great location and the environment is very quiet.",
          "Also the room is big, the view is very beautiful, nice breakfast and the location is in a side street, so it’s quiet."
        ]
      },
      {
        "aspect": "FAC_BATH",
        "group": "FACILITY",
        "measurement_scale": "Bathroom & Sanitary Area",
        "matched_sentences": 282033,
        "unique_opinions": 256847,
        "evidence_used_for_summary": 5000,
        "cluster_weight": 0.03861211217978742,
        "cec": 0.6547614820040027,
        "asc_contribution": 0.02743745494044317,
        "summary": [
          "The room was very clean and comfortable.",
          "The room was very comfortable and clean.",
          "The room was very spacious and clean."
        ]
      },
      {
        "aspect": "AM_ENT",
        "group": "AMENITY",
        "measurement_scale": "Entertainment & Recreation",
        "matched_sentences": 35237,
        "unique_opinions": 34153,
        "evidence_used_for_summary": 5000,
        "cluster_weight": 0.032357898795504624,
        "cec": 0.494055239527853,
        "asc_contribution": 0.027152204893084515,
        "summary": [
          "We liked the location it's within easy walking distance to the beach and restaurants - it's very private and nice gardens - the staff are friendly and the breakfast is good - the pool is fabulous and the room was clean and comfortable For us the bed was a bit hard and the breakfast menu was very limited",
          "The room was very clean and comfortable, the shower was amazing and there was a good TV and AC.",
          "The apartment I stayed in was great - clean, spacious and airy and light, with great facilities and a nice little balcony; the location is very good - on a side street in a bustling area and close to the tourist nightlife area as well as a nice park; the staff were pleasant and helpful - the girl came when I had an issue with the TV and she helped me organise a taxi to the airport when I was leaving and was responsive to my messages and the guy who met me to give me the keys was also very friendly and helpful...All in all I would definitely recommend this place in Ho Chi Minh..."
        ]
      },
      {
        "aspect": "EXP_SAFETY",
        "group": "EXPERIENCE",
        "measurement_scale": "Subjective Safety Feeling",
        "matched_sentences": 91744,
        "unique_opinions": 79994,
        "evidence_used_for_summary": 5000,
        "cluster_weight": 0.03499610806947721,
        "cec": 0.7430003796813353,
        "asc_contribution": 0.027146737706398253,
        "summary": [
          "The room was very clean and the bed comfortable.",
          "The bed was very comfortable and the room clean.",
          "The room was clean and the bed very comfortable."
        ]
      }
    ]
  },
  {
    "file": "hotel_review3.csv",
    "folder": "C:\\Users\\dso3hc\\Downloads\\Implement\\SemAE\\outputs\\hasos_english_only\\hotel_review3",
    "stats": {
      "input_csv": "C:\\Users\\dso3hc\\Downloads\\Implement\\hotel_review3.csv",
      "detector_rule": "English-like if repaired text has at least 8 alphabetic chars, ASCII-letter ratio >= 0.86, at least 3 normalized tokens, and either 2 common English marker hits, or 1 marker plus 1 hotel-domain hit, or 2 hotel-domain hits with ASCII ratio >= 0.94.",
      "total_rows": 591023,
      "nonempty_reviews": 591023,
      "english_reviews": 538515,
      "english_sentences": 3146670,
      "rejected_reviews": 52508,
      "reject_reasons": {
        "low_ascii_letter_ratio": 51845,
        "no_english_sentences": 206,
        "not_enough_english_markers": 457
      },
      "top_english_hotels": [
        {
          "hotel_id": "tripadvisor_96021",
          "english_reviews": 4541
        },
        {
          "hotel_id": "tripadvisor_140411",
          "english_reviews": 3923
        },
        {
          "hotel_id": "tripadvisor_10987",
          "english_reviews": 2891
        },
        {
          "hotel_id": "tripadvisor_01306",
          "english_reviews": 2594
        },
        {
          "hotel_id": "tripadvisor_429195",
          "english_reviews": 2500
        },
        {
          "hotel_id": "tripadvisor_89558",
          "english_reviews": 2487
        },
        {
          "hotel_id": "tripadvisor_440716",
          "english_reviews": 2462
        },
        {
          "hotel_id": "tripadvisor_123184",
          "english_reviews": 2347
        },
        {
          "hotel_id": "tripadvisor_125833",
          "english_reviews": 2337
        },
        {
          "hotel_id": "tripadvisor_458627",
          "english_reviews": 2305
        },
        {
          "hotel_id": "tripadvisor_512633",
          "english_reviews": 2186
        },
        {
          "hotel_id": "tripadvisor_309771",
          "english_reviews": 2143
        },
        {
          "hotel_id": "tripadvisor_451055",
          "english_reviews": 2085
        },
        {
          "hotel_id": "tripadvisor_443184",
          "english_reviews": 2075
        },
        {
          "hotel_id": "tripadvisor_461935",
          "english_reviews": 2029
        },
        {
          "hotel_id": "tripadvisor_437644",
          "english_reviews": 2002
        },
        {
          "hotel_id": "tripadvisor_481391",
          "english_reviews": 1888
        },
        {
          "hotel_id": "tripadvisor_465062",
          "english_reviews": 1876
        },
        {
          "hotel_id": "tripadvisor_60408",
          "english_reviews": 1855
        },
        {
          "hotel_id": "tripadvisor_55081",
          "english_reviews": 1805
        }
      ],
      "sample_kept": [
        {
          "ref_id": "tripadvisor_00001_0",
          "hotel_id": "tripadvisor_00001",
          "reason": "common_english_markers",
          "ascii_letter_ratio": 1.0,
          "marker_hits": 13,
          "hotel_hits": 8,
          "review": "Good hotel i have ever stayed in Vietnam, good pice , friendly staffs , nice room with lake view , i stayed in 3 nights with all of good felling , breakfast was delicious , many choices . i will be back soon ."
        },
        {
          "ref_id": "tripadvisor_00002_1",
          "hotel_id": "tripadvisor_00002",
          "reason": "common_english_markers",
          "ascii_letter_ratio": 1.0,
          "marker_hits": 34,
          "hotel_hits": 6,
          "review": "This place was very nice. Our bedroom were clean and comfortable. The bathtub was great and something you won’t find in comparable hotels in the area. It is a just few minute walk to the center, but it’s very close and you are a bit removed from the noise. There are some great places to eat within a 5 minute walk. It’s a great place for a few days in Hanoi."
        },
        {
          "ref_id": "tripadvisor_00002_2",
          "hotel_id": "tripadvisor_00002",
          "reason": "common_english_markers",
          "ascii_letter_ratio": 1.0,
          "marker_hits": 21,
          "hotel_hits": 4,
          "review": "It was a amazing hotel. They helped very good at the reception. The lady kept smiling, even when our questions were a bit too much. Next to thay the rooms were very clean and got a room upgraded. In the end, a good option!"
        }
      ],
      "sample_rejected": [
        {
          "ref_id": "tripadvisor_00046_95",
          "reason": "low_ascii_letter_ratio",
          "ascii_letter_ratio": 0.5533333333333333,
          "marker_hits": 7,
          "hotel_hits": 1,
          "review": "everything is good ! they gave me warmest greeting ! i recommend this hotel extremly if you visit Hanoi. 모든 것이 좋았습니다 같은 가격에 방도 업그레이드 해주고, 늦은 시간에 체크인 했음에도 친절히 설명해주었습니다. 하노이에 간다면 이곳에 머무는 것을 추천합니다."
        },
        {
          "ref_id": "tripadvisor_00382_411",
          "reason": "low_ascii_letter_ratio",
          "ascii_letter_ratio": 0.7749077490774908,
          "marker_hits": 22,
          "hotel_hits": 6,
          "review": "John He was good customer service and i had good experience this hotel. Room was clean and good location. Also right beside of there there is Catholic church. So you can bisit there to see how things go :) And John will teach you where you go! And fun place :) Thank you! 완전 좋은 경험 했습니다! 존이라는 친구를 찾아서 물어보세요! 어디로 가야 하는지 뭘 해야 하는지! 다 친절하게 알려줍니다!~ 호텔도 깨끗하고 좋았습니다"
        },
        {
          "ref_id": "tripadvisor_00382_431",
          "reason": "low_ascii_letter_ratio",
          "ascii_letter_ratio": 0.8095238095238095,
          "marker_hits": 46,
          "hotel_hits": 7,
          "review": "The location is very good, easy access to most of the places we wanted to go. Room was clean but my friend thinks the plugs were not very convenient for charging cellphones. Maybe the building is not designed for a hotel at the first place. The staff are all great and helpful indeed. They offered quite good prices when we wanted to book two more nights. Ms. Na was willing to explain things and showed her enthusiasm as a young employee. I think the hotel is run by a group of smart and hardworking young people. I would love to come back next time when visiting Hanoi. 地點佳，容易抵達老城區及還劍湖區。 工作人員年輕友善且樂意幫忙，Ms. Na. 是新員工，展現了極大的笑容與熱忱。對於年輕人來說非常可貴。 房間大小可接受，室內環境也算乾淨。早餐頗豐盛且味道不錯，看得出很用心。以小旅館來說非常值得肯定。 若有機會會願意再度造訪。"
        }
      ],
      "english_ratio": 0.9111574338054526
    },
    "overall": {
      "review_count": 538515,
      "sentence_count": 3146670,
      "aspect_summary_cover": 0.7539144537824739,
      "macro_cec": 0.5712519365071903,
      "weighted_cec": 0.5727799730232973,
      "matched_aspects": 29,
      "aspect_count": 29,
      "rouge_note": "ROUGE-1/2/L from the SemAE paper requires human gold summaries; this CSV has reviews only, so this trial reports image-formula CEC/ASC instead.",
      "scoring_note": "unique_opinions and cluster_weight are counted on the whole input; summary/CEC/ASC use a capped representative evidence set per aspect.",
      "language_filter": "english",
      "include_vietnamese_aliases": false
    },
    "top_aspects": [
      {
        "aspect": "EXP_OVERALL",
        "group": "EXPERIENCE",
        "measurement_scale": "Overall Stay Experience",
        "matched_sentences": 463676,
        "unique_opinions": 426041,
        "evidence_used_for_summary": 5000,
        "cluster_weight": 0.038301151420177273,
        "cec": 0.4846750330128727,
        "asc_contribution": 0.03173335918829758,
        "summary": [
          "The Essence was a wonderful place to stay for our trip to Hanoi!",
          "I stayed here for 3 nights, and it was the best decision i ever made for a stay in Hanoi, from the time of our inquiries they responds very quickly, the transfer from airport to the hotel, the hotel staff they are all accommodating and exceeded our expectation our room was so clean and the bed was so comfy, they also so have the indigo spa which soothes our muscle pain after long day of tour , they greeted me and make my birthday more special, they offer day tours that fits to our length of stay, definitely will recommend to others and will sure be back soon and stay again at Acoustic Hotel and Spa.",
          "My husband and I were staying in Hanoi for our honeymoon and we would have to say that the experience we had at this hotel was amazing."
        ]
      },
      {
        "aspect": "FAC_BUILDING",
        "group": "FACILITY",
        "measurement_scale": "Building Infrastructure",
        "matched_sentences": 183422,
        "unique_opinions": 176500,
        "evidence_used_for_summary": 5000,
        "cluster_weight": 0.035697336619555764,
        "cec": 0.6431292035837431,
        "asc_contribution": 0.030447409024016235,
        "summary": [
          "The hotel is in a great location for the Old Quarter of Hanoi.",
          "The hotel is in a great location in the old quarter.",
          "The location is great, very close to the lake and right in the heart of the old quarter."
        ]
      },
      {
        "aspect": "AM_POOL",
        "group": "AMENITY",
        "measurement_scale": "Pool & Water Facilities",
        "matched_sentences": 378267,
        "unique_opinions": 345571,
        "evidence_used_for_summary": 5000,
        "cluster_weight": 0.03768259999131128,
        "cec": 0.6467853700156982,
        "asc_contribution": 0.030115731886175078,
        "summary": [
          "The hotel is very comfortable and the rooms are spacious and clean.",
          "The room very clean and comfortable and the breakfast was very nice.",
          "The room was very clean and comfortable."
        ]
      },
      {
        "aspect": "AM_FOOD",
        "group": "AMENITY",
        "measurement_scale": "Food & Beverage",
        "matched_sentences": 554481,
        "unique_opinions": 512579,
        "evidence_used_for_summary": 5000,
        "cluster_weight": 0.03884755206649655,
        "cec": 0.5450105923613587,
        "asc_contribution": 0.029882436619714927,
        "summary": [
          "The staff is very friendly and the breakfast was great.",
          "The food in the restaurant was delicious and a good selection at the breakfast.",
          "The room was clean and the food in the restaurant was good."
        ]
      },
      {
        "aspect": "FAC_BATH",
        "group": "FACILITY",
        "measurement_scale": "Bathroom & Sanitary Area",
        "matched_sentences": 406277,
        "unique_opinions": 372007,
        "evidence_used_for_summary": 5000,
        "cluster_weight": 0.03790041208800518,
        "cec": 0.6404378267788776,
        "asc_contribution": 0.029184334613532335,
        "summary": [
          "The hotel is very comfortable and the rooms are spacious and clean.",
          "The room very clean and comfortable and the breakfast was very nice.",
          "The room was very comfortable and clean."
        ]
      },
      {
        "aspect": "SER_ATTITUDE",
        "group": "SERVICE",
        "measurement_scale": "Staff Attitude & Hospitality",
        "matched_sentences": 547246,
        "unique_opinions": 499367,
        "evidence_used_for_summary": 5000,
        "cluster_weight": 0.03877039156679429,
        "cec": 0.6234166428459714,
        "asc_contribution": 0.027941300094440735,
        "summary": [
          "The staff at the hotel was very friendly and helpful.",
          "The staff was very friendly and helpful.",
          "The staff were very friendly and helpful."
        ]
      },
      {
        "aspect": "FAC_ROOM",
        "group": "FACILITY",
        "measurement_scale": "Room, Bed & Sleep Quality",
        "matched_sentences": 809873,
        "unique_opinions": 755457,
        "evidence_used_for_summary": 5000,
        "cluster_weight": 0.03999362764495228,
        "cec": 0.5805900338921969,
        "asc_contribution": 0.027740570469179875,
        "summary": [
          "The hotel is very comfortable and the rooms are spacious and clean.",
          "The location was good and the rooms very clean and comfortable.",
          "The room was very clean and comfortable."
        ]
      },
      {
        "aspect": "FAC_INTERIOR",
        "group": "FACILITY",
        "measurement_scale": "Interior Design & Ambience",
        "matched_sentences": 168493,
        "unique_opinions": 161667,
        "evidence_used_for_summary": 5000,
        "cluster_weight": 0.035437958140887856,
        "cec": 0.6129360760759569,
        "asc_contribution": 0.027678540800991455,
        "summary": [
          "The Hotel is beautiful, the rooms are comfortable and very clean.",
          "The hotel is in a great location and the rooms were clean and modern.",
          "The hotel is beautiful staff a friendly and the rooms are very clean ."
        ]
      },
      {
        "aspect": "FAC_ENV",
        "group": "FACILITY",
        "measurement_scale": "Noise & Environmental Comfort",
        "matched_sentences": 104738,
        "unique_opinions": 100817,
        "evidence_used_for_summary": 5000,
        "cluster_weight": 0.034042612928207885,
        "cec": 0.5922755286385787,
        "asc_contribution": 0.02747539627741234,
        "summary": [
          "The location of the hotel is in the Old Quarter, but on a very quiet street.",
          "The hotel is in a great location for the old quarter and my room was very quiet.",
          "The room was clean and quiet and the location of the hotel is good for exploring the Old Quarter."
        ]
      },
      {
        "aspect": "AM_WELLNESS",
        "group": "AMENITY",
        "measurement_scale": "Gym, Spa & Wellness Facilities",
        "matched_sentences": 149927,
        "unique_opinions": 144104,
        "evidence_used_for_summary": 5000,
        "cluster_weight": 0.035098146827722665,
        "cec": 0.5303335943245021,
        "asc_contribution": 0.027125053761362792,
        "summary": [
          "The hotel is in a great location and the rooms were clean and modern.",
          "The staff was very professional and the hotel was clean and comfortable.",
          "The staff of the hotel is friendly and very professional."
        ]
      }
    ]
  }
]
